gwstreamlit/__init__.py
gwstreamlit/_create_ui.py
gwstreamlit/_utils.py
gwstreamlit/constants.py
gwstreamlit/core.py
gwstreamlit/models.py
gwstreamlit/process_templates.py
gwstreamlit/utils.py
gwstreamlit-0.0.15.dist-info/LICENSE
gwstreamlit-0.0.15.dist-info/METADATA
gwstreamlit-0.0.15.dist-info/WHEEL
gwstreamlit-0.0.15.dist-info/RECORD
